examples/CambioComparisons.py
examples/MakeEmissionScenario.py
meclib/__init__.py
meclib/cl.py
meclib-0.1.1.dist-info/METADATA
meclib-0.1.1.dist-info/WHEEL
meclib-0.1.1.dist-info/top_level.txt
meclib-0.1.1.dist-info/RECORD
