Metadata-Version: 2.4
Name: meclib
Version: 0.1.1
Summary: Code for Modeling Earth's Climate course
Author-email: Steven Neshyba <sneshyba@gmail.com>
Requires-Python: >=3.8
Requires-Dist: numpy
Requires-Dist: matplotlib
Requires-Dist: pandas
Requires-Dist: pint
